artpy/__init__.py
artpy/_modidx.py
artpy/core.py
airt-0.0.1.dist-info/LICENSE
airt-0.0.1.dist-info/METADATA
airt-0.0.1.dist-info/WHEEL
airt-0.0.1.dist-info/entry_points.txt
airt-0.0.1.dist-info/top_level.txt
airt-0.0.1.dist-info/RECORD
